LICENSE
MANIFEST.in
setup.py
Nawa.egg-info/PKG-INFO
Nawa.egg-info/SOURCES.txt
Nawa.egg-info/dependency_links.txt
Nawa.egg-info/requires.txt
Nawa.egg-info/top_level.txt
nawa/__init__.py
nawa/cc.py
nawa/core.py
nawa/utils.py
nawa/bin/nawa_admin.py
nawa/bin/nawa_admin.py
nawa/bin/project_templates/nawa_config.yaml
nawa/profile_templates/cgi/.htaccess
nawa/profile_templates/cgi/nawaapi.py
nawa/profile_templates/cgi/nawaapi_ep.py
nawa/profile_templates/cgi/cache/.htaccess
nawa/tools/nawa_cache_clean_ep.py
nawa/tools/nawa_cgi_serv.py