Metadata-Version: 1.0
Name: Nawa
Version: 1.0.0.b090711064517
Summary: Nawa is a simple Python web framework that designed for our ecological scripting life.
Home-page: http://code.google.com/p/nawa-framework/
Author: ruby-U
Author-email: ruby.u.g@gmail.com
License: MIT
Platform: Any
Classifier: Development Status :: 4 - Beta
Classifier: Environment :: Console
Classifier: License :: OSI Approved :: MIT License
Classifier: Operating System :: OS Independent
Classifier: Topic :: Internet :: WWW/HTTP :: Dynamic Content :: CGI Tools/Libraries
Classifier: Topic :: Software Development :: Libraries :: Python Modules
Classifier: Topic :: Software Development :: Libraries :: Application Frameworks
